cython_dev_tools/__init__.py
cython_dev_tools/common.py
cython_dev_tools/cytools.py
cython_dev_tools/logs.py
cython_dev_tools/settings.py
cython_dev_tools/_boilerplate_package/Makefile
cython_dev_tools/_boilerplate_package/cytools_script.py
cython_dev_tools/_boilerplate_package/setup.py
cython_dev_tools/_boilerplate_package/bp_cython/__init__.py
cython_dev_tools/_boilerplate_package/bp_cython/bp_cython_class.pxd
cython_dev_tools/_boilerplate_package/bp_cython/bp_cython_class.pyx
cython_dev_tools/_boilerplate_package/bp_cython/bp_cython_module.pxd
cython_dev_tools/_boilerplate_package/bp_cython/bp_cython_module.pyx
cython_dev_tools/_boilerplate_package/bp_cython/tests/__init__.py
cython_dev_tools/_boilerplate_package/bp_cython/tests/test_bp_cython_class.py
cython_dev_tools/_boilerplate_package/bp_cython/tests/test_bp_cython_class_.pyx
cython_dev_tools/_boilerplate_package/bp_cython/tests/test_bp_cython_class_mock.py
cython_dev_tools/_boilerplate_package/bp_cython/tests/test_bp_cython_class_mock_.pyx
cython_dev_tools/_boilerplate_package/bp_cython/tests/test_bp_cython_module.py
cython_dev_tools/_boilerplate_package/bp_cython/tests/test_bp_cython_module_.pyx
cython_dev_tools/_cy_tools_samples/__init__.py
cython_dev_tools/_cy_tools_samples/cy_memory_unsafe.pyx
cython_dev_tools/_cy_tools_samples/debugging/__init__.py
cython_dev_tools/_cy_tools_samples/debugging/abort.pyx
cython_dev_tools/_cy_tools_samples/debugging/assertions.pyx
cython_dev_tools/_cy_tools_samples/debugging/breakpoint.pyx
cython_dev_tools/_cy_tools_samples/debugging/errors.pyx
cython_dev_tools/_cy_tools_samples/debugging/memory_leaks.pyx
cython_dev_tools/_cy_tools_samples/debugging/segfault.pyx
cython_dev_tools/_cy_tools_samples/low_level/__init__.py
cython_dev_tools/_cy_tools_samples/low_level/arrays.pyx
cython_dev_tools/_cy_tools_samples/low_level/arrays_resize.pyx
cython_dev_tools/_cy_tools_samples/low_level/dynamic_memory.pyx
cython_dev_tools/_cy_tools_samples/low_level/hello_world.pyx
cython_dev_tools-0.6.7.dist-info/LICENSE
cython_dev_tools-0.6.7.dist-info/METADATA
cython_dev_tools-0.6.7.dist-info/WHEEL
cython_dev_tools-0.6.7.dist-info/entry_points.txt
cython_dev_tools-0.6.7.dist-info/top_level.txt
cython_dev_tools-0.6.7.dist-info/RECORD
