Metadata-Version: 2.1
Name: cython-dev-tools
Version: 0.6.7
Summary: Cython development toolkit (debugger, profiler, coverage, unit tests)
Author-email: Alex Veden <i@alexveden.com>
License: MIT License
Project-URL: Homepage, https://github.com/alexveden/cython-dev-tools
Keywords: cython,debugger,profiler,coverage,unit tests
Classifier: License :: OSI Approved :: MIT License
Classifier: Programming Language :: Python
Classifier: Programming Language :: Python :: 3
Requires-Python: >=3.6
License-File: LICENSE
Requires-Dist: cython (<3.0.0)
Requires-Dist: numpy
Requires-Dist: pytest
Requires-Dist: coverage
Requires-Dist: line-profiler
